pyuhoo/__init__.py
pyuhoo/api.py
pyuhoo/cli.py
pyuhoo/client.py
pyuhoo/consts.py
pyuhoo/device.py
pyuhoo/endpoints.py
pyuhoo/errors.py
pyuhoo/util.py
pyuhoo-0.0.5.dist-info/entry_points.txt
pyuhoo-0.0.5.dist-info/LICENSE
pyuhoo-0.0.5.dist-info/WHEEL
pyuhoo-0.0.5.dist-info/METADATA
pyuhoo-0.0.5.dist-info/RECORD
